{
  "parent": "minecraft:recipes/root",
  "rewards": {
    "recipes": [
      "consumablesandcharms:hell_steak_from_smoking"
    ]
  },
  "criteria": {
    "has_hell_meat": {
      "trigger": "minecraft:inventory_changed",
      "conditions": {
        "items": [
          {
            "item": "consumablesandcharms:hell_meat"
          }
        ]
      }
    },
    "has_the_recipe": {
      "trigger": "minecraft:recipe_unlocked",
      "conditions": {
        "recipe": "consumablesandcharms:hell_steak_from_smoking"
      }
    }
  },
  "requirements": [
    [
      "has_hell_meat",
      "has_the_recipe"
    ]
  ]
}